awhd8uwgadhuyawd/__init__.py
awhd8uwgadhuyawd/__main__.py
awhd8uwgadhuyawd/fib.py
awhd8uwgadhuyawd-0.1.0.dist-info/METADATA
awhd8uwgadhuyawd-0.1.0.dist-info/WHEEL
awhd8uwgadhuyawd-0.1.0.dist-info/RECORD
